{
"meta":{"test_sets":[],"test_metrics":[],"learn_metrics":[{"best_value":"Min","name":"RMSE"}],"launch_mode":"Train","parameters":"","iteration_count":100,"learn_sets":["learn"],"name":"experiment"},
"iterations":[
{"learn":[14.005006],"iteration":0,"passed_time":0.001106376497,"remaining_time":0.1095312732},
{"learn":[13.14441192],"iteration":1,"passed_time":0.00212286644,"remaining_time":0.1040204556},
{"learn":[12.34258257],"iteration":2,"passed_time":0.003043414923,"remaining_time":0.09840374916},
{"learn":[11.64527793],"iteration":3,"passed_time":0.003775219154,"remaining_time":0.09060525968},
{"learn":[11.02766183],"iteration":4,"passed_time":0.004795477205,"remaining_time":0.09111406689},
{"learn":[10.43485794],"iteration":5,"passed_time":0.005716309644,"remaining_time":0.08955551776},
{"learn":[9.890641275],"iteration":6,"passed_time":0.0067387305,"remaining_time":0.08952884808},
{"learn":[9.492161212],"iteration":7,"passed_time":0.007746780298,"remaining_time":0.08908797343},
{"learn":[9.105082953],"iteration":8,"passed_time":0.008626765539,"remaining_time":0.0872261849},
{"learn":[8.674157135],"iteration":9,"passed_time":0.009549382174,"remaining_time":0.08594443957},
{"learn":[8.341743544],"iteration":10,"passed_time":0.01054618349,"remaining_time":0.0853282119},
{"learn":[8.049372916],"iteration":11,"passed_time":0.01155049642,"remaining_time":0.08470364041},
{"learn":[7.757318612],"iteration":12,"passed_time":0.01252522009,"remaining_time":0.08382262676},
{"learn":[7.522206899],"iteration":13,"passed_time":0.01344680502,"remaining_time":0.08260180224},
{"learn":[7.297756655],"iteration":14,"passed_time":0.01437100992,"remaining_time":0.08143572286},
{"learn":[7.088359431],"iteration":15,"passed_time":0.01527149968,"remaining_time":0.08017537334},
{"learn":[6.882113791],"iteration":16,"passed_time":0.01626391482,"remaining_time":0.07940617233},
{"learn":[6.704728832],"iteration":17,"passed_time":0.01717209792,"remaining_time":0.07822844609},
{"learn":[6.563881962],"iteration":18,"passed_time":0.01817429253,"remaining_time":0.07747987867},
{"learn":[6.418790279],"iteration":19,"passed_time":0.01919051177,"remaining_time":0.07676204707},
{"learn":[6.315756953],"iteration":20,"passed_time":0.02008953632,"remaining_time":0.07557492233},
{"learn":[6.210157751],"iteration":21,"passed_time":0.02101029398,"remaining_time":0.0744910423},
{"learn":[6.115058449],"iteration":22,"passed_time":0.02199145874,"remaining_time":0.07362357926},
{"learn":[6.014819884],"iteration":23,"passed_time":0.02293831583,"remaining_time":0.07263800012},
{"learn":[5.93117229],"iteration":24,"passed_time":0.02396894399,"remaining_time":0.07190683196},
{"learn":[5.844857622],"iteration":25,"passed_time":0.02504080931,"remaining_time":0.07126999572},
{"learn":[5.771145213],"iteration":26,"passed_time":0.02615162405,"remaining_time":0.07070624281},
{"learn":[5.704018229],"iteration":27,"passed_time":0.02720212067,"remaining_time":0.0699483103},
{"learn":[5.665806474],"iteration":28,"passed_time":0.02824068069,"remaining_time":0.06914097687},
{"learn":[5.616500369],"iteration":29,"passed_time":0.0292036741,"remaining_time":0.06814190624},
{"learn":[5.558023666],"iteration":30,"passed_time":0.03019566046,"remaining_time":0.06720969586},
{"learn":[5.510080976],"iteration":31,"passed_time":0.03110365805,"remaining_time":0.06609527335},
{"learn":[5.468747792],"iteration":32,"passed_time":0.03213244143,"remaining_time":0.06523859321},
{"learn":[5.429275534],"iteration":33,"passed_time":0.03308849683,"remaining_time":0.06423061149},
{"learn":[5.402117324],"iteration":34,"passed_time":0.03407122335,"remaining_time":0.06327512908},
{"learn":[5.367635151],"iteration":35,"passed_time":0.03502840606,"remaining_time":0.06227272188},
{"learn":[5.345181232],"iteration":36,"passed_time":0.03606654772,"remaining_time":0.06141060827},
{"learn":[5.319151269],"iteration":37,"passed_time":0.03715063076,"remaining_time":0.06061418703},
{"learn":[5.296134146],"iteration":38,"passed_time":0.03808477699,"remaining_time":0.05956849734},
{"learn":[5.269629003],"iteration":39,"passed_time":0.03902509171,"remaining_time":0.05853763757},
{"learn":[5.251147059],"iteration":40,"passed_time":0.03994617403,"remaining_time":0.05748351873},
{"learn":[5.248003302],"iteration":41,"passed_time":0.04034499243,"remaining_time":0.05571451336},
{"learn":[5.232376509],"iteration":42,"passed_time":0.04124465967,"remaining_time":0.05467315352},
{"learn":[5.213524255],"iteration":43,"passed_time":0.04224261575,"remaining_time":0.05376332913},
{"learn":[5.189691584],"iteration":44,"passed_time":0.04319373313,"remaining_time":0.0527923405},
{"learn":[5.166052198],"iteration":45,"passed_time":0.04423204895,"remaining_time":0.0519245792},
{"learn":[5.140406659],"iteration":46,"passed_time":0.04528585935,"remaining_time":0.05106703288},
{"learn":[5.118929684],"iteration":47,"passed_time":0.04621100131,"remaining_time":0.05006191808},
{"learn":[5.108792602],"iteration":48,"passed_time":0.04711347877,"remaining_time":0.04903647791},
{"learn":[5.098141225],"iteration":49,"passed_time":0.04803253459,"remaining_time":0.04803253459},
{"learn":[5.085926393],"iteration":50,"passed_time":0.0492286992,"remaining_time":0.04729816198},
{"learn":[5.067816804],"iteration":51,"passed_time":0.05017862018,"remaining_time":0.04631872632},
{"learn":[5.049834901],"iteration":52,"passed_time":0.05111287716,"remaining_time":0.04532651371},
{"learn":[5.03838627],"iteration":53,"passed_time":0.05214242249,"remaining_time":0.04441761916},
{"learn":[5.033534248],"iteration":54,"passed_time":0.05276646698,"remaining_time":0.04317256389},
{"learn":[5.023726885],"iteration":55,"passed_time":0.05383191866,"remaining_time":0.04229650752},
{"learn":[5.01290392],"iteration":56,"passed_time":0.05494649583,"remaining_time":0.04145086528},
{"learn":[5.005569127],"iteration":57,"passed_time":0.05586230886,"remaining_time":0.04045201676},
{"learn":[4.989969032],"iteration":58,"passed_time":0.05682121897,"remaining_time":0.03948593183},
{"learn":[4.976762446],"iteration":59,"passed_time":0.05778948073,"remaining_time":0.03852632049},
{"learn":[4.967222715],"iteration":60,"passed_time":0.05876209933,"remaining_time":0.03756921105},
{"learn":[4.954407599],"iteration":61,"passed_time":0.05973963986,"remaining_time":0.03661461798},
{"learn":[4.942125056],"iteration":62,"passed_time":0.06065610409,"remaining_time":0.03562342621},
{"learn":[4.930230716],"iteration":63,"passed_time":0.061648063,"remaining_time":0.03467703544},
{"learn":[4.921695642],"iteration":64,"passed_time":0.06265474886,"remaining_time":0.03373717246},
{"learn":[4.906405625],"iteration":65,"passed_time":0.06368092931,"remaining_time":0.03280532722},
{"learn":[4.894330248],"iteration":66,"passed_time":0.06460678684,"remaining_time":0.03182125322},
{"learn":[4.88211557],"iteration":67,"passed_time":0.06566644674,"remaining_time":0.03090185729},
{"learn":[4.877946398],"iteration":68,"passed_time":0.0666488647,"remaining_time":0.02994369284},
{"learn":[4.863182126],"iteration":69,"passed_time":0.06763011938,"remaining_time":0.02898433688},
{"learn":[4.84646533],"iteration":70,"passed_time":0.06862222689,"remaining_time":0.0280287969},
{"learn":[4.838014752],"iteration":71,"passed_time":0.069605297,"remaining_time":0.02706872661},
{"learn":[4.82981137],"iteration":72,"passed_time":0.07064116038,"remaining_time":0.02612755247},
{"learn":[4.817094767],"iteration":73,"passed_time":0.07169308814,"remaining_time":0.0251894634},
{"learn":[4.808314151],"iteration":74,"passed_time":0.07262731483,"remaining_time":0.02420910494},
{"learn":[4.796235023],"iteration":75,"passed_time":0.07357646913,"remaining_time":0.02323467446},
{"learn":[4.784434534],"iteration":76,"passed_time":0.07454803046,"remaining_time":0.02226759352},
{"learn":[4.774402487],"iteration":77,"passed_time":0.07543873508,"remaining_time":0.02127759194},
{"learn":[4.76731896],"iteration":78,"passed_time":0.0764170915,"remaining_time":0.02031340407},
{"learn":[4.75934113],"iteration":79,"passed_time":0.07730924714,"remaining_time":0.01932731178},
{"learn":[4.754106378],"iteration":80,"passed_time":0.07835486159,"remaining_time":0.01837953544},
{"learn":[4.744002932],"iteration":81,"passed_time":0.0793146586,"remaining_time":0.01741053481},
{"learn":[4.731700554],"iteration":82,"passed_time":0.08029856543,"remaining_time":0.01644669412},
{"learn":[4.723284153],"iteration":83,"passed_time":0.08121827624,"remaining_time":0.01547014786},
{"learn":[4.712232782],"iteration":84,"passed_time":0.08204582884,"remaining_time":0.01447867568},
{"learn":[4.703046867],"iteration":85,"passed_time":0.0830390135,"remaining_time":0.01351797894},
{"learn":[4.698601855],"iteration":86,"passed_time":0.08395791692,"remaining_time":0.01254543586},
{"learn":[4.692429407],"iteration":87,"passed_time":0.08482394852,"remaining_time":0.01156690207},
{"learn":[4.675027364],"iteration":88,"passed_time":0.08573839099,"remaining_time":0.01059687978},
{"learn":[4.662368584],"iteration":89,"passed_time":0.0865416293,"remaining_time":0.009615736589},
{"learn":[4.646206172],"iteration":90,"passed_time":0.08751714238,"remaining_time":0.008655541554},
{"learn":[4.641245848],"iteration":91,"passed_time":0.08845568899,"remaining_time":0.007691799043},
{"learn":[4.633900435],"iteration":92,"passed_time":0.08939149543,"remaining_time":0.006728392129},
{"learn":[4.624738236],"iteration":93,"passed_time":0.0903004755,"remaining_time":0.005763860139},
{"learn":[4.612798287],"iteration":94,"passed_time":0.09123378122,"remaining_time":0.004801777959},
{"learn":[4.605222001],"iteration":95,"passed_time":0.09216157818,"remaining_time":0.003840065757},
{"learn":[4.601725912],"iteration":96,"passed_time":0.09317829907,"remaining_time":0.002881803064},
{"learn":[4.59722371],"iteration":97,"passed_time":0.09406817359,"remaining_time":0.001919758645},
{"learn":[4.580235665],"iteration":98,"passed_time":0.09506905726,"remaining_time":0.0009602935077},
{"learn":[4.57591791],"iteration":99,"passed_time":0.09600764836,"remaining_time":0}
]}